cnabs_test/__init__.py
cnabs_test/assets.py
cnabs_test/deals.py
cnabs_test/org.py
cnabs_test/projects.py
cnabs_test/securities.py
cnabs_test/tools.py
cnabssdk/__init__.py
cnabssdk/assets.py
cnabssdk/clients.py
cnabssdk/configs.py
cnabssdk/deals.py
cnabssdk/entries.py
cnabssdk/organizations.py
cnabssdk/projects.py
cnabssdk/securities.py
cnabssdk/common/__init__.py
cnabssdk/common/utility.py
cnabs_sdk-0.0.5.dist-info/METADATA
cnabs_sdk-0.0.5.dist-info/WHEEL
cnabs_sdk-0.0.5.dist-info/top_level.txt
cnabs_sdk-0.0.5.dist-info/RECORD
