Metadata-Version: 2.1
Name: cnabs-sdk
Version: 0.0.5
Summary: CNABS OPENAPI SDK
Home-page: https://github.com/cnabs
Author: Bo Pan
Author-email: bo.pan@cn-abs.com
License: GPLv3
Platform: UNKNOWN
Classifier: Programming Language :: Python :: 3
Classifier: License :: OSI Approved :: GNU General Public License v3 (GPLv3)
Classifier: Operating System :: OS Independent
Requires-Python: >=3.3
Requires-Dist: requests (>=2.2.0)
